travis2docker/__init__.py
travis2docker/__main__.py
travis2docker/cli.py
travis2docker/exceptions.py
travis2docker/git_run.py
travis2docker/travis2docker.py
travis2docker/docker_helper/build.py
travis2docker/templates/.coveragerc
travis2docker/templates/10-build.sh
travis2docker/templates/20-run.sh
travis2docker/templates/Dockerfile
travis2docker/templates/Dockerfile_deployv
travis2docker/templates/build.sh
travis2docker/templates/entrypoint.sh
travis2docker/templates/entrypoint_deployv.sh
travis2docker/templates/rvm_env.sh
travis2docker/templates/.vscode/extensions.json
travis2docker/templates/.vscode/launch.json
travis2docker/templates/.vscode/settings.json
travis2docker/travis-ci-apt-source-whitelist/.git
travis2docker/travis-ci-apt-source-whitelist/.gitignore
travis2docker/travis-ci-apt-source-whitelist/.travis.yml
travis2docker/travis-ci-apt-source-whitelist/LICENSE
travis2docker/travis-ci-apt-source-whitelist/README.md
travis2docker/travis-ci-apt-source-whitelist/add_all.rb
travis2docker/travis-ci-apt-source-whitelist/ubuntu.json
travis2docker/travis-ci-apt-source-whitelist/bin/travis-add-source
travis2docker-6.4.23.dist-info/licenses/AUTHORS.rst
travis2docker-6.4.23.dist-info/licenses/LICENSE
travis2docker-6.4.23.dist-info/METADATA
travis2docker-6.4.23.dist-info/WHEEL
travis2docker-6.4.23.dist-info/entry_points.txt
travis2docker-6.4.23.dist-info/top_level.txt
travis2docker-6.4.23.dist-info/RECORD
